pysparkparquettable/__init__.py
pysparkparquettable/table.py
pysparkparquettable/table_dst.py
pysparkparquettable/table_src.py
pysparkparquettable/table_src_dst.py
pysparkparquettable/table_src_dst_limit.py
pysparkparquettable-0.0.1.dist-info/METADATA
pysparkparquettable-0.0.1.dist-info/WHEEL
pysparkparquettable-0.0.1.dist-info/top_level.txt
pysparkparquettable-0.0.1.dist-info/RECORD
