Metadata-Version: 2.1
Name: pysparkparquettable
Version: 0.0.1
Requires-Dist: logclshelper
Requires-Dist: pysparkhelper
Requires-Dist: pysparkhdfshelper
Requires-Dist: pysparkparquethelper
